rape.py
rape3d-0.1.0.dist-info/METADATA
rape3d-0.1.0.dist-info/WHEEL
rape3d-0.1.0.dist-info/top_level.txt
rape3d-0.1.0.dist-info/RECORD
