Metadata-Version: 2.4
Name: rape3D
Version: 0.1.0
Summary: Pacote 3D sinistro
Author: Davi Carozo Rocha Sobral
Classifier: Programming Language :: Python :: 3
Classifier: Operating System :: OS Independent
Requires-Python: >=3.7
Dynamic: author
Dynamic: classifier
Dynamic: description
Dynamic: description-content-type
Dynamic: requires-python
Dynamic: summary
